keras2onnx/__init__.py
keras2onnx/_builtin.py
keras2onnx/cli.py
keras2onnx/funcbook.py
keras2onnx/main.py
keras2onnx/parser.py
keras2onnx/subgraph.py
keras2onnx/topology.py
keras2onnx/wrapper.py
keras2onnx/common/__init__.py
keras2onnx/common/cvtfunc.py
keras2onnx/common/data_types.py
keras2onnx/common/interim.py
keras2onnx/common/intop.py
keras2onnx/common/onnx_ops.py
keras2onnx/common/utils.py
keras2onnx/ke2onnx/__init__.py
keras2onnx/ke2onnx/activation.py
keras2onnx/ke2onnx/adv_activation.py
keras2onnx/ke2onnx/batch_norm.py
keras2onnx/ke2onnx/bidirectional.py
keras2onnx/ke2onnx/common.py
keras2onnx/ke2onnx/conv.py
keras2onnx/ke2onnx/crop.py
keras2onnx/ke2onnx/dense.py
keras2onnx/ke2onnx/dot.py
keras2onnx/ke2onnx/embedding.py
keras2onnx/ke2onnx/gru.py
keras2onnx/ke2onnx/lstm.py
keras2onnx/ke2onnx/main.py
keras2onnx/ke2onnx/merge.py
keras2onnx/ke2onnx/pooling.py
keras2onnx/ke2onnx/simplernn.py
keras2onnx/ke2onnx/upsample.py
keras2onnx/ke2onnx/zeropad.py
keras2onnx/ktf2onnx/tf2onnx/__init__.py
keras2onnx/ktf2onnx/tf2onnx/constants.py
keras2onnx/ktf2onnx/tf2onnx/convert.py
keras2onnx/ktf2onnx/tf2onnx/graph.py
keras2onnx/ktf2onnx/tf2onnx/graph_builder.py
keras2onnx/ktf2onnx/tf2onnx/graph_matcher.py
keras2onnx/ktf2onnx/tf2onnx/handler.py
keras2onnx/ktf2onnx/tf2onnx/loader.py
keras2onnx/ktf2onnx/tf2onnx/schemas.py
keras2onnx/ktf2onnx/tf2onnx/shape_inference.py
keras2onnx/ktf2onnx/tf2onnx/tfonnx.py
keras2onnx/ktf2onnx/tf2onnx/utils.py
keras2onnx/ktf2onnx/tf2onnx/verbose_logging.py
keras2onnx/ktf2onnx/tf2onnx/version.py
keras2onnx/ktf2onnx/tf2onnx/custom_opsets/__init__.py
keras2onnx/ktf2onnx/tf2onnx/custom_opsets/ms.py
keras2onnx/ktf2onnx/tf2onnx/onnx_opset/__init__.py
keras2onnx/ktf2onnx/tf2onnx/onnx_opset/common.py
keras2onnx/ktf2onnx/tf2onnx/onnx_opset/controlflow.py
keras2onnx/ktf2onnx/tf2onnx/onnx_opset/generator.py
keras2onnx/ktf2onnx/tf2onnx/onnx_opset/logical.py
keras2onnx/ktf2onnx/tf2onnx/onnx_opset/math.py
keras2onnx/ktf2onnx/tf2onnx/onnx_opset/misc.py
keras2onnx-1.6.1.dist-info/LICENSE
keras2onnx-1.6.1.dist-info/METADATA
keras2onnx-1.6.1.dist-info/WHEEL
keras2onnx-1.6.1.dist-info/top_level.txt
keras2onnx-1.6.1.dist-info/RECORD
