Metadata-Version: 2.1
Name: keras2onnx
Version: 1.6.1
Summary: Converts Machine Learning models to ONNX for use in Windows ML
Home-page: https://github.com/onnx/keras-onnx
Author: Microsoft Corporation
Author-email: winmlcvt@microsoft.com
License: MIT License
Platform: UNKNOWN
Classifier: Development Status :: 4 - Beta
Classifier: Environment :: Console
Classifier: Intended Audience :: Developers
Classifier: Operating System :: POSIX
Classifier: Operating System :: Microsoft :: Windows
Classifier: Programming Language :: Python :: 3 :: Only
Classifier: Programming Language :: Python :: 3.5
Classifier: Programming Language :: Python :: 3.6
Classifier: License :: OSI Approved :: MIT License
Requires-Dist: numpy
Requires-Dist: protobuf
Requires-Dist: requests
Requires-Dist: onnx
Requires-Dist: onnxconverter-common (<1.7.0,>=1.6.0)
Requires-Dist: fire
